adc-0.0.3.dist-info/DESCRIPTION.rst
adc-0.0.3.dist-info/METADATA
adc-0.0.3.dist-info/RECORD
adc-0.0.3.dist-info/WHEEL
adc-0.0.3.dist-info/metadata.json
adc-0.0.3.dist-info/top_level.txt
genesis/__init__.py
genesis/streaming.py
