Metadata-Version: 2.0
Name: adc
Version: 0.0.3
Summary: Genesis Platform client libraries
Home-page: https://github.com/astronomy-commons/genesis-client
Author: Mario Juric
Author-email: mjuric@astro.washington.edu
License: MIT
Platform: UNKNOWN
Classifier: Programming Language :: Python :: 3
Classifier: License :: OSI Approved :: BSD License
Classifier: Development Status :: 3 - Alpha
Classifier: Operating System :: POSIX :: Linux
Classifier: Operating System :: MacOS :: MacOS X
Requires-Dist: confluent-kafka
Requires-Dist: fastavro
Requires-Dist: tqdm
